fracodim/TreeNode.py
fracodim/__init__.py
fracodim/correlationDimension.py
fracodim/listNode.py
fracodim-1.5.dist-info/LICENSE
fracodim-1.5.dist-info/METADATA
fracodim-1.5.dist-info/WHEEL
fracodim-1.5.dist-info/top_level.txt
fracodim-1.5.dist-info/RECORD
