Metadata-Version: 2.1
Name: fracodim
Version: 1.5
Summary: Structural package of the box-counting plot method used in fractal correlation dimension estimation.
Home-page: https://github.com/renangcf/fracodim
Author: Renan Gomes
Author-email: renangcfreitas@gmail.com
Classifier: Programming Language :: Python :: 3
Classifier: License :: OSI Approved :: MIT License
Classifier: Operating System :: OS Independent
Requires-Python: >=3.6
License-File: LICENSE
Requires-Dist: numpy
Requires-Dist: scipy
